hint_cli/__init__.py
hint_cli/hint.py
hint_cli/parser.py
hint_cli/repo.py
hint_cli/style.py
tests/__init__.py
tests/test_hint.py
tests/test_parser.py
tests/test_repo.py
tests/test_style.py
hint_cli-0.11.1.dist-info/LICENSE
hint_cli-0.11.1.dist-info/METADATA
hint_cli-0.11.1.dist-info/WHEEL
hint_cli-0.11.1.dist-info/entry_points.txt
hint_cli-0.11.1.dist-info/top_level.txt
hint_cli-0.11.1.dist-info/RECORD
