Metadata-Version: 2.1
Name: hint-cli
Version: 0.11.1
Summary: Get help and examples for commands from the command line, without switching context or applications.
Author: Andrew Garner
Author-email: 1242023+agarthetiger@users.noreply.github.com
License: MIT License
Project-URL: homepage, https://github.com/agarthetiger/hint/
Project-URL: repository, https://github.com/agarthetiger/hint/
Project-URL: documentation, https://agarthetiger.github.io/hint/
Keywords: cli,help
Classifier: Development Status :: 4 - Beta
Classifier: Environment :: Console
Classifier: Intended Audience :: End Users/Desktop
Classifier: Operating System :: OS Independent
Classifier: License :: OSI Approved :: MIT License
Classifier: Programming Language :: Python :: 3.9
Classifier: Topic :: Utilities
Requires-Python: >=3.9
License-File: LICENSE
Requires-Dist: gitpython ~=3.1.7
Requires-Dist: pygments ~=2.7
Requires-Dist: click ~=8.0
Provides-Extra: build
Requires-Dist: build ; extra == 'build'
Provides-Extra: tests
Requires-Dist: pytest ~=7.1.2 ; extra == 'tests'
Requires-Dist: pytest-cov ~=3.0.0 ; extra == 'tests'
